fb2maker/__init__.py
fb2maker/__version__.py
fb2maker/Author.py
fb2maker/builders/__init__.py
fb2maker/builders/BuildAuthorName.py
fb2maker/builders/DocumentInfoBuilder.py
fb2maker/builders/TitleInfoBuilder.py
fb2maker/constants.py
fb2maker/DocumentInfo.py
fb2maker/FB2Builder.py
fb2maker/FB2ImageDataclass.py
fb2maker/FictionBook2.py
fb2maker/FictionBook2dataclass.py
fb2maker/TitleInfo.py
fb2maker-0.1.1.dist-info/LICENSE
fb2maker-0.1.1.dist-info/METADATA
fb2maker-0.1.1.dist-info/WHEEL
fb2maker-0.1.1.dist-info/RECORD
