Metadata-Version: 2.1
Name: fb2maker
Version: 0.1.1
Summary: Fork FB2 with updates
License: MIT
Author: DustGalaxy
Author-email: 103292379+DustGalaxy@users.noreply.github.com
Requires-Python: >=3.10,<4.0
Classifier: License :: OSI Approved :: MIT License
Classifier: Programming Language :: Python :: 3
Classifier: Programming Language :: Python :: 3.10
Classifier: Programming Language :: Python :: 3.11
Classifier: Programming Language :: Python :: 3.12
Requires-Dist: iso-639 (==0.4.5)
